{
  "version": 2,
  "projects": {
    "about-us": {
      "root": "libs/about-us",
      "sourceRoot": "libs/about-us/src",
      "projectType": "library",
      "targets": {
        "lint": {
          "executor": "@nrwl/linter:eslint",
          "options": {
            "lintFilePatterns": ["libs/about-us/**/*.{ts,tsx,js,jsx}"]
          }
        },
        "test": {
          "executor": "@nrwl/jest:jest",
          "outputs": ["coverage/libs/about-us"],
          "options": {
            "jestConfig": "libs/about-us/jest.config.js",
            "passWithNoTests": true
          }
        }
      }
    },
    "alpsbte-api": {
      "root": "apps/alpsbte-api",
      "sourceRoot": "apps/alpsbte-api/src",
      "projectType": "application",
      "targets": {
        "build": {
          "executor": "@nrwl/node:build",
          "outputs": ["{options.outputPath}"],
          "options": {
            "outputPath": "dist/apps/alpsbte-api",
            "main": "apps/alpsbte-api/src/main.ts",
            "tsConfig": "apps/alpsbte-api/tsconfig.app.json",
            "assets": ["apps/alpsbte-api/src/assets"],
            "generatePackageJson": true
          },
          "configurations": {
            "production": {
              "optimization": true,
              "extractLicenses": true,
              "inspect": false,
              "fileReplacements": [
                {
                  "replace": "apps/alpsbte-api/src/environments/environment.ts",
                  "with": "apps/alpsbte-api/src/environments/environment.prod.ts"
                }
              ]
            }
          }
        },
        "serve": {
          "executor": "@nrwl/node:execute",
          "options": {
            "buildTarget": "alpsbte-api:build"
          }
        },
        "lint": {
          "executor": "@nrwl/linter:eslint",
          "options": {
            "lintFilePatterns": ["apps/alpsbte-api/**/*.ts"]
          }
        },
        "test": {
          "executor": "@nrwl/jest:jest",
          "outputs": ["coverage/apps/alpsbte-api"],
          "options": {
            "jestConfig": "apps/alpsbte-api/jest.config.js",
            "passWithNoTests": true
          }
        }
      }
    },
    "alpsbte-web": {
      "root": "apps/alpsbte-web",
      "sourceRoot": "apps/alpsbte-web/src",
      "projectType": "application",
      "targets": {
        "build": {
          "executor": "@nrwl/web:build",
          "outputs": ["{options.outputPath}"],
          "options": {
            "outputPath": "dist/apps/alpsbte-web",
            "index": "apps/alpsbte-web/src/index.html",
            "main": "apps/alpsbte-web/src/main.tsx",
            "polyfills": "apps/alpsbte-web/src/polyfills.ts",
            "tsConfig": "apps/alpsbte-web/tsconfig.app.json",
            "assets": [
              "apps/alpsbte-web/src/favicon.ico",
              "apps/alpsbte-web/src/assets"
            ],
            "styles": ["apps/alpsbte-web/src/styles.scss"],
            "scripts": [],
            "webpackConfig": "webpack.custom.config.js"
          },
          "configurations": {
            "production": {
              "fileReplacements": [
                {
                  "replace": "apps/alpsbte-web/src/environments/environment.ts",
                  "with": "apps/alpsbte-web/src/environments/environment.prod.ts"
                }
              ],
              "optimization": true,
              "outputHashing": "all",
              "sourceMap": false,
              "extractCss": true,
              "namedChunks": false,
              "extractLicenses": true,
              "vendorChunk": false,
              "budgets": [
                {
                  "type": "initial",
                  "maximumWarning": "1000kb",
                  "maximumError": "5mb"
                }
              ]
            }
          }
        },
        "serve": {
          "executor": "@nrwl/web:dev-server",
          "options": {
            "buildTarget": "alpsbte-web:build",
            "hmr": true,
            "proxyConfig": "apps/alpsbte-web/proxy.conf.json"
          },
          "configurations": {
            "production": {
              "buildTarget": "alpsbte-web:build:production",
              "hmr": false
            }
          }
        },
        "lint": {
          "executor": "@nrwl/linter:eslint",
          "options": {
            "lintFilePatterns": ["apps/alpsbte-web/**/*.{ts,tsx,js,jsx}"]
          }
        },
        "test": {
          "executor": "@nrwl/jest:jest",
          "outputs": ["coverage/apps/alpsbte-web"],
          "options": {
            "jestConfig": "apps/alpsbte-web/jest.config.js",
            "passWithNoTests": true
          }
        }
      }
    },
    "application": {
      "root": "libs/application",
      "sourceRoot": "libs/application/src",
      "projectType": "library",
      "targets": {
        "lint": {
          "executor": "@nrwl/linter:eslint",
          "options": {
            "lintFilePatterns": ["libs/application/**/*.{ts,tsx,js,jsx}"]
          }
        },
        "test": {
          "executor": "@nrwl/jest:jest",
          "outputs": ["coverage/libs/application"],
          "options": {
            "jestConfig": "libs/application/jest.config.js",
            "passWithNoTests": true
          }
        }
      }
    },
    "contact": {
      "root": "libs/contact",
      "sourceRoot": "libs/contact/src",
      "projectType": "library",
      "targets": {
        "lint": {
          "executor": "@nrwl/linter:eslint",
          "options": {
            "lintFilePatterns": ["libs/contact/**/*.{ts,tsx,js,jsx}"]
          }
        },
        "test": {
          "executor": "@nrwl/jest:jest",
          "outputs": ["coverage/libs/contact"],
          "options": {
            "jestConfig": "libs/contact/jest.config.js",
            "passWithNoTests": true
          }
        }
      }
    },
    "downloads": {
      "root": "libs/downloads",
      "sourceRoot": "libs/downloads/src",
      "projectType": "library",
      "targets": {
        "lint": {
          "executor": "@nrwl/linter:eslint",
          "options": {
            "lintFilePatterns": ["libs/downloads/**/*.{ts,tsx,js,jsx}"]
          }
        },
        "test": {
          "executor": "@nrwl/jest:jest",
          "outputs": ["coverage/libs/downloads"],
          "options": {
            "jestConfig": "libs/downloads/jest.config.js",
            "passWithNoTests": true
          }
        }
      }
    },
    "error": {
      "root": "libs/error",
      "sourceRoot": "libs/error/src",
      "projectType": "library",
      "targets": {
        "lint": {
          "executor": "@nrwl/linter:eslint",
          "options": {
            "lintFilePatterns": ["libs/error/**/*.{ts,tsx,js,jsx}"]
          }
        },
        "test": {
          "executor": "@nrwl/jest:jest",
          "outputs": ["coverage/libs/error"],
          "options": {
            "jestConfig": "libs/error/jest.config.js",
            "passWithNoTests": true
          }
        }
      }
    },
    "faq": {
      "root": "libs/faq",
      "sourceRoot": "libs/faq/src",
      "projectType": "library",
      "targets": {
        "lint": {
          "executor": "@nrwl/linter:eslint",
          "options": {
            "lintFilePatterns": ["libs/faq/**/*.{ts,tsx,js,jsx}"]
          }
        },
        "test": {
          "executor": "@nrwl/jest:jest",
          "outputs": ["coverage/libs/faq"],
          "options": {
            "jestConfig": "libs/faq/jest.config.js",
            "passWithNoTests": true
          }
        }
      }
    },
    "gallery": {
      "root": "libs/gallery",
      "sourceRoot": "libs/gallery/src",
      "projectType": "library",
      "targets": {
        "lint": {
          "executor": "@nrwl/linter:eslint",
          "options": {
            "lintFilePatterns": ["libs/gallery/**/*.{ts,tsx,js,jsx}"]
          }
        },
        "test": {
          "executor": "@nrwl/jest:jest",
          "outputs": ["coverage/libs/gallery"],
          "options": {
            "jestConfig": "libs/gallery/jest.config.js",
            "passWithNoTests": true
          }
        }
      }
    },
    "home": {
      "root": "libs/home",
      "sourceRoot": "libs/home/src",
      "projectType": "library",
      "targets": {
        "lint": {
          "executor": "@nrwl/linter:eslint",
          "options": {
            "lintFilePatterns": ["libs/home/**/*.{ts,tsx,js,jsx}"]
          }
        },
        "test": {
          "executor": "@nrwl/jest:jest",
          "outputs": ["coverage/libs/home"],
          "options": {
            "jestConfig": "libs/home/jest.config.js",
            "passWithNoTests": true
          }
        }
      }
    },
    "loader": {
      "root": "libs/loader",
      "sourceRoot": "libs/loader/src",
      "projectType": "library",
      "targets": {
        "lint": {
          "executor": "@nrwl/linter:eslint",
          "options": {
            "lintFilePatterns": ["libs/loader/**/*.{ts,tsx,js,jsx}"]
          }
        },
        "test": {
          "executor": "@nrwl/jest:jest",
          "outputs": ["coverage/libs/loader"],
          "options": {
            "jestConfig": "libs/loader/jest.config.js",
            "passWithNoTests": true
          }
        }
      }
    },
    "router": {
      "root": "libs/router",
      "sourceRoot": "libs/router/src",
      "projectType": "library",
      "targets": {
        "lint": {
          "executor": "@nrwl/linter:eslint",
          "options": {
            "lintFilePatterns": ["libs/router/**/*.{ts,tsx,js,jsx}"]
          }
        },
        "test": {
          "executor": "@nrwl/jest:jest",
          "outputs": ["coverage/libs/router"],
          "options": {
            "jestConfig": "libs/router/jest.config.js",
            "passWithNoTests": true
          }
        }
      }
    },
    "shared-components": {
      "root": "libs/shared/components",
      "sourceRoot": "libs/shared/components/src",
      "projectType": "library",
      "targets": {
        "lint": {
          "executor": "@nrwl/linter:eslint",
          "options": {
            "lintFilePatterns": ["libs/shared/components/**/*.{ts,tsx,js,jsx}"]
          }
        },
        "test": {
          "executor": "@nrwl/jest:jest",
          "outputs": ["coverage/libs/shared/components"],
          "options": {
            "jestConfig": "libs/shared/components/jest.config.js",
            "passWithNoTests": true
          }
        },
        "storybook": {
          "executor": "@nrwl/storybook:storybook",
          "options": {
            "uiFramework": "@storybook/react",
            "port": 4400,
            "config": {
              "configFolder": "libs/shared/components/.storybook"
            }
          },
          "configurations": {
            "ci": {
              "quiet": true
            }
          }
        },
        "build-storybook": {
          "executor": "@nrwl/storybook:build",
          "outputs": ["{options.outputPath}"],
          "options": {
            "uiFramework": "@storybook/react",
            "outputPath": "dist/storybook/shared-components",
            "config": {
              "configFolder": "libs/shared/components/.storybook"
            }
          },
          "configurations": {
            "ci": {
              "quiet": true
            }
          }
        }
      }
    },
    "shared-config": {
      "root": "libs/shared/config",
      "sourceRoot": "libs/shared/config/src",
      "projectType": "library",
      "targets": {
        "lint": {
          "executor": "@nrwl/linter:eslint",
          "options": {
            "lintFilePatterns": ["libs/shared/config/**/*.ts"]
          }
        },
        "test": {
          "executor": "@nrwl/jest:jest",
          "outputs": ["coverage/libs/shared/config"],
          "options": {
            "jestConfig": "libs/shared/config/jest.config.js",
            "passWithNoTests": true
          }
        }
      }
    },
    "shared-language": {
      "root": "libs/shared/language",
      "sourceRoot": "libs/shared/language/src",
      "projectType": "library",
      "targets": {
        "lint": {
          "executor": "@nrwl/linter:eslint",
          "options": {
            "lintFilePatterns": ["libs/shared/language/**/*.ts"]
          }
        },
        "test": {
          "executor": "@nrwl/jest:jest",
          "outputs": ["coverage/libs/shared/language"],
          "options": {
            "jestConfig": "libs/shared/language/jest.config.js",
            "passWithNoTests": true
          }
        }
      }
    },
    "shared-stores": {
      "root": "libs/shared/stores",
      "sourceRoot": "libs/shared/stores/src",
      "projectType": "library",
      "targets": {
        "lint": {
          "executor": "@nrwl/linter:eslint",
          "options": {
            "lintFilePatterns": ["libs/shared/stores/**/*.ts"]
          }
        },
        "test": {
          "executor": "@nrwl/jest:jest",
          "outputs": ["coverage/libs/shared/stores"],
          "options": {
            "jestConfig": "libs/shared/stores/jest.config.js",
            "passWithNoTests": true
          }
        }
      }
    },
    "shared-theme": {
      "root": "libs/shared/theme",
      "sourceRoot": "libs/shared/theme/src",
      "projectType": "library",
      "targets": {
        "lint": {
          "executor": "@nrwl/linter:eslint",
          "options": {
            "lintFilePatterns": ["libs/shared/theme/**/*.{ts,tsx,js,jsx}"]
          }
        },
        "test": {
          "executor": "@nrwl/jest:jest",
          "outputs": ["coverage/libs/shared/theme"],
          "options": {
            "jestConfig": "libs/shared/theme/jest.config.js",
            "passWithNoTests": true
          }
        }
      }
    },
    "shared-util": {
      "root": "libs/shared/util",
      "sourceRoot": "libs/shared/util/src",
      "projectType": "library",
      "targets": {
        "lint": {
          "executor": "@nrwl/linter:eslint",
          "options": {
            "lintFilePatterns": ["libs/shared/util/**/*.ts"]
          }
        },
        "test": {
          "executor": "@nrwl/jest:jest",
          "outputs": ["coverage/libs/shared/util"],
          "options": {
            "jestConfig": "libs/shared/util/jest.config.js",
            "passWithNoTests": true
          }
        }
      }
    }
  },
  "cli": {
    "defaultCollection": "@nrwl/react"
  },
  "generators": {
    "@nrwl/react": {
      "application": {
        "style": "scss",
        "linter": "eslint",
        "babel": true
      },
      "component": {
        "style": "scss"
      },
      "library": {
        "style": "scss",
        "linter": "eslint"
      }
    }
  },
  "storybook": {
    "executor": "@nrwl/storybook:storybook",
    "options": {
      "uiFramework": "@storybook/react",
      "port": 4400,
      "config": {
        "configFolder": "libs/ui/.storybook"
      }
    },
    "configurations": {
      "ci": {
        "quiet": true
      }
    }
  },
  "build-storybook": {
    "executor": "@nrwl/storybook:build",
    "outputs": ["{options.outputPath}"],
    "options": {
      "uiFramework": "@storybook/react",
      "outputPath": "dist/storybook/ui",
      "config": {
        "configFolder": "libs/ui/.storybook"
      }
    },
    "configurations": {
      "ci": {
        "quiet": true
      }
    }
  },
  "defaultProject": "alpsbte-web"
}
